{"trial_id": "95e068f6490935fa0176885a0776a080", "hyperparameters": {"space": [{"class_name": "Choice", "config": {"name": "activation", "default": "relu", "conditions": [], "values": ["relu", "tanh", "sigmoid"], "ordered": false}}, {"class_name": "Int", "config": {"name": "first_units", "default": null, "conditions": [], "min_value": 1, "max_value": 80, "step": 5, "sampling": null}}, {"class_name": "Int", "config": {"name": "num_layers", "default": null, "conditions": [], "min_value": 1, "max_value": 6, "step": 1, "sampling": null}}, {"class_name": "Int", "config": {"name": "units_0", "default": null, "conditions": [], "min_value": 1, "max_value": 100, "step": 5, "sampling": null}}, {"class_name": "Int", "config": {"name": "units_1", "default": null, "conditions": [], "min_value": 1, "max_value": 100, "step": 5, "sampling": null}}, {"class_name": "Int", "config": {"name": "units_2", "default": null, "conditions": [], "min_value": 1, "max_value": 100, "step": 5, "sampling": null}}, {"class_name": "Int", "config": {"name": "units_3", "default": null, "conditions": [], "min_value": 1, "max_value": 100, "step": 5, "sampling": null}}, {"class_name": "Int", "config": {"name": "units_4", "default": null, "conditions": [], "min_value": 1, "max_value": 100, "step": 5, "sampling": null}}, {"class_name": "Int", "config": {"name": "units_5", "default": null, "conditions": [], "min_value": 1, "max_value": 100, "step": 5, "sampling": null}}], "values": {"activation": "relu", "first_units": 41, "num_layers": 5, "units_0": 96, "units_1": 6, "units_2": 96, "units_3": 21, "units_4": 41, "units_5": 11, "tuner/epochs": 20, "tuner/initial_epoch": 0, "tuner/bracket": 0, "tuner/round": 0}}, "metrics": {"metrics": {"loss": {"direction": "min", "observations": [{"value": [0.4740450978279114], "step": 0}]}, "accuracy": {"direction": "max", "observations": [{"value": [0.9651298522949219], "step": 0}]}, "val_loss": {"direction": "min", "observations": [{"value": [0.749119758605957], "step": 0}]}, "val_accuracy": {"direction": "max", "observations": [{"value": [0.7890378832817078], "step": 0}]}}}, "score": 0.7890378832817078, "best_step": 0, "status": "COMPLETED"}